Workbook

Sheet Notas
A1: Correcoes aplicadas e pendencias
A2: Mass Total Services Inc - EIN 93-3675961 - Form 1120-S 2025 (ano-calendario, regime de caixa)
A5: DECLARACAO RETIFICADORA (1120-S 2025, EIN 93-3675961) - o que muda:
A6: 1. Pagina 1, item F (Total assets): 7,909 -> 126,931.
A7: 2. Schedule L inicio: caixa 77,714 e retained earnings 77,714 (estava tudo zero).
A8: 3. Schedule L fim: Loans to shareholders (L7) 119,022; financiamento do BMW sai da L16 e vai para a L20; retained earnings 87,412.
A9: 4. Schedule M-1, M-2, Schedule K e K-1: sem alteracao (distribuicoes 220,000; AAA final 87,412).
A10: 5. Form 4562: BMW na Part V (listed property). K-1: tirar 'PRESIDENT' do nome do socio.
A11: 6. Massachusetts: Schedules A, B e D com os novos saldos; excise continua 456.
A13: PARA O EMPRESTIMO AO SOCIO SER ACEITO PELO IRS:
A14: a. Nota promissoria assinada (valor 119,022, juros pela taxa AFR do IRS, prazo de pagamento).
A15: b. Cobrar juros pela AFR - sem juros, o IRS imputa juros (IRC 7872).
... A22: g. Contrato do financiamento: saldo em 31/12/2025 e juros pagos.

Sheet Dados
A1: Dados de entrada (azul = digitado; amarelo = confirmar com o cliente)
A2: Mass Total Services Inc - EIN 93-3675961 - Form 1120-S 2025 (ano-calendario, regime de caixa)
A5: Item | B5: Valor | C5: Fonte / observacao
A6: Receita bruta (1120-S L1c) | B6: 445989 | C6: 1120-S pag. 1
A7: Custo das mercadorias - compras (1125-A) | B7: 128185 | C7: 1125-A L2
A8: Reparos e manutencao (L9) | B8: 801 | C8: 1120-S pag. 1
A9: Impostos e licencas (L12) | B9: 4880 | C9: Wks Tax/Lic
A10: Outras despesas (L20) | B10: 42905 | C10: Statement #2
A11: BMW - custo (em servico 08/15/2025) | B11: 39520 | C11: Depreciation detail
A12: BMW - % uso comercial | B12: 1 | C12: CONFIRMAR com log de milhas (Form 4562 Part V)
A13: BMW e carro de passeio ate 6,000 lbs GVWR? (1=sim, 0=nao) | B13: 0 | C13: CONFIRMAR modelo. 1 = aplica limite IRC 280F
A14: Limite 280F 1o ano com bonus (Rev. Proc. 2025-16) | B14: 20200 | C14: carros em servico em 2025
A15: Distribuicoes registradas (Wks DIST) | B15: 220000 | C15: K 16d original
A16: AAA inicio do ano (M-2 L1) | B16: 77714 | C16: 2024: 78,491 - 777 nao dedutivel
A17: Caixa 31/12/2025 (extrato) | B17: 7909 | C17: Sch L / MA Sch A L16
... A22: Retiradas do socio sem registro: 1 = emprestimo ao socio, 0 = distribuicao | B22: 1 | C22: Distribuicoes de 2025 foram so 220,000 -> emprestimo
A24: Depreciacao calculada (federal) | B24: =IF(Dados!$B$13=1,MIN(Dados!$B$11*Dados!$B$12,Dados!$B$14),Dados!$B$11*Dados!$B$12)

Sheet DRE
A1: Demonstracao de Resultado 2025 (Income Statement per books)
A2: Mass Total Services Inc - EIN 93-3675961 - Form 1120-S 2025 (ano-calendario, regime de caixa)
A5: Conta | B5: 2025
A6: Receita bruta (Gross receipts) | B6: =Dados!$B$6
A7: (-) Custo das mercadorias vendidas (COGS) | B7: =-Dados!$B$7
A8: Lucro bruto (Gross profit) | B8: =B6+B7
A9: (-) Reparos e manutencao | B9: =-Dados!$B$8
A10: (-) Impostos e licencas | B10: =-Dados!$B$9
A11: (-) Depreciacao (BMW) | B11: =-Dados!$B$24
A12: (-) Outras despesas | B12: =-Dados!$B$10+Dados!$B$20
A13: (-) Despesas nao dedutiveis | B13: =-Dados!$B$20
A14: Lucro liquido contabil (Net income per books) | B14: =SUM(B8:B13)
A15: Lucro fiscal - 1120-S L22 (lucro contabil + nao dedutiveis) | B15: =B14+Dados!$B$20

Sheet Conciliacao
A1: Conciliacao de caixa - retiradas do socio nao registradas
A2: Mass Total Services Inc - EIN 93-3675961 - Form 1120-S 2025 (ano-calendario, regime de caixa)
A3: Saida de caixa sem despesa documentada = distribuicao ao socio (IRC 1368)
A5: Movimento | B5: Valor
A6: Caixa inicio (31/12/2024) | B6: =Dados!$B$18
A7: (+) Lucro liquido contabil | B7: =DRE!B14
A8: (+) Depreciacao (nao e saida de caixa) | B8: =Dados!$B$24
A9: (-) Compra BMW | B9: =-Dados!$B$11
A10: (+) Financiamento BMW | B10: =Dados!$B$19
A11: (-) Distribuicoes registradas | B11: =-Dados!$B$15
A12: Caixa que deveria existir em 31/12/2025 | B12: =SUM(B6:B11)
A13: Caixa real em 31/12/2025 (extrato) | B13: =Dados!$B$17
A14: Retiradas do socio nao registradas | B14: =B12-B13
A16: TOTAL DE DISTRIBUICOES 2025 (K 16d / K-1 16D) | B16: =Dados!$B$15+IF(Dados!$B$22=1,0,B14)
A17: Emprestimo ao socio (Sch L linha 7) | B17: =IF(Dados!$B$22=1,B14,0)

Sheet Schedule L
A1: Schedule L - Balance Sheets per Books (correto)
A2: Mass Total Services Inc - EIN 93-3675961 - Form 1120-S 2025 (ano-calendario, regime de caixa)
A3: Colunas (a)/(c) = bruto; (b)/(d) = liquido, como no formulario
A5: Linha | B5: (a) Inicio bruto | C5: (b) Inicio | D5: (c) Fim bruto | E5: (d) Fim
A6: 1 Cash | C6: =Dados!$B$18 | E6: =Dados!$B$17
A7: 7 Loans to shareholders | C7: 0 | E7: =Conciliacao!B17
A8: 10a Buildings and other depreciable assets (BMW) | B8: 0 | D8: =Dados!$B$11
A9: 10b Less accumulated depreciation (liquido em b/d) | B9: 0 | C9: =B8+B9 | D9: =-Dados!$B$24 | E9: =D8+D9
A10: 15 Total assets | C10: =C6+C7+C9 | E10: =E6+E7+E9
A12: 20 Mortgages, notes, bonds payable >= 1 yr (financ. BMW) | C12: 0 | E12: =Dados!$B$19
A13: 22 Capital stock | C13: =Dados!$B$21 | E13: =Dados!$B$21
A14: 24 Retained earnings | C14: =Dados!$B$18-Dados!$B$21 | E14: =C14+DRE!B14-Conciliacao!$B$16
A15: 27 Total liabilities and shareholders' equity | C15: =SUM(C12:C14) | E15: =SUM(E12:E14)
A17: Diferenca (tem que ser zero) | C17: =C10-C15 | E17: =E10-E15

Sheet Schedule M-1
A1: Schedule M-1 - Reconciliation of Income per Books with Income per Return
A2: Mass Total Services Inc - EIN 93-3675961 - Form 1120-S 2025 (ano-calendario, regime de caixa)
A5: Linha | B5: Valor
A6: 1 Net income (loss) per books | B6: =DRE!B14
A7: 2 Income on Sch K not recorded on books | B7: 0
A8: 3 Expenses on books not on Sch K (nao dedutiveis) | B8: =Dados!$B$20
A9: 4 Add lines 1 through 3 | B9: =SUM(B6:B8)
A10: 5 Income on books not on Sch K | B10: 0
A11: 6 Deductions on Sch K not charged against book income | B11: 0
A12: 7 Add lines 5 and 6 | B12: =B10+B11
A13: 8 Income (loss) Schedule K line 18 | B13: =B9-B12

Sheet Schedule M-2
A1: Schedule M-2 - AAA / OAA
A2: Mass Total Services Inc - EIN 93-3675961 - Form 1120-S 2025 (ano-calendario, regime de caixa)
A3: Linha 7 limitada a linha 6: distribuicao nao deixa o AAA negativo (Reg. 1.1368-2(a)(3)(iii))
A5: Linha | B5: (a) AAA | C5: (d) OAA
A6: 1 Balance at beginning of tax year | B6: =Dados!$B$16 | C6: 0
A7: 2 Ordinary income from page 1, line 22 | B7: ='Schedule M-1'!B13
A8: 3 Other additions | B8: 0 | C8: 0
A9: 4 Loss from page 1, line 22 | B9: 0
A10: 5 Other reductions (nao dedutiveis) | B10: =-Dados!$B$20 | C10: 0
A11: 6 Combine lines 1 through 5 | B11: =SUM(B6:B10) | C11: =SUM(C6:C10)
A12: 7 Distributions (limitado ao AAA) | B12: =MAX(0,MIN(B11,Conciliacao!$B$16)) | C12: 0
A13: 8 Balance at end of tax year | B13: =B11-B12 | C13: =C11-C12
A15: Distribuicao acima do AAA (nao entra no M-2) | B15: =Conciliacao!$B$16-B12
A16: Conferencia: RE fim (Sch L) = AAA fim - excesso? | B16: =IF('Schedule L'!E14=B13+C13-B15,"OK","VERIFICAR")

Sheet Base do Socio
A1: Base das acoes do socio (Form 7203) - Erli Marques de Morais, 100%
A2: Mass Total Services Inc - EIN 93-3675961 - Form 1120-S 2025 (ano-calendario, regime de caixa)
A3: Ordem: aumentos -> distribuicoes -> nao dedutiveis -> perdas (IRC 1368(d), Reg. 1.1367-1(f))
A5: Item | B5: Valor
A6: Capital aportado na abertura | B6: =Dados!$B$21
A7: (+) Lucro 2024 menos nao dedutiveis 2024 | B7: =Dados!$B$16
A8: Base no inicio de 2025 | B8: =B6+B7
A9: (+) Lucro ordinario 2025 (K-1 box 1) | B9: ='Schedule M-1'!B13
A10: Base antes das distribuicoes | B10: =B8+B9
A11: (-) Distribuicoes 2025 (K-1 box 16D) | B11: =-Conciliacao!$B$16
A12: Distribuicao isenta (ate a base) | B12: =MIN(B10,Conciliacao!$B$16)
A13: GANHO DE CAPITAL LONGO PRAZO DO SOCIO (excesso sobre a base) | B13: =MAX(0,Conciliacao!$B$16-B10)
A14: (-) Nao dedutiveis 2025 | B14: =-Dados!$B$20
A15: Base no fim de 2025 | B15: =MAX(0,B10-Conciliacao!$B$16-Dados!$B$20)
